treeg/__init__.py
treeg/treeg_estimator.py
treeg-1.0.dist-info/LICENSE.txt
treeg-1.0.dist-info/METADATA
treeg-1.0.dist-info/WHEEL
treeg-1.0.dist-info/top_level.txt
treeg-1.0.dist-info/RECORD
